{"leagues": [{"id": "23", "uid": "s:20~l:23", "name": "NCAA - Football", "abbreviation": "NCAAF", "midsizeName": "NCAA Football", "slug": "college-football", "season": {"year": 2022, "startDate": "2022-07-01T07:00Z", "endDate": "2023-01-11T07:59Z", "displayName": "2022", "type": {"id": "4", "type": 4, "name": "Off Season", "abbreviation": "off"}}, "logos": [{"href": "https://a3.espncdn.com/redesign/assets/img/icons/ESPN-icon-football-college.png", "width": 500, "height": 500, "alt": "", "rel": ["full", "default"], "lastUpdated": "2021-08-03T15:56Z"}], "calendarType": "list", "calendarIsWhitelist": true, "calendarStartDate": "2021-07-01T07:00Z", "calendarEndDate": "2022-01-12T07:59Z", "calendar": [{"label": "Regular Season", "value": "2", "startDate": "2021-07-24T07:00Z", "endDate": "2021-12-17T07:59Z", "entries": [{"label": "Week 1", "alternateLabel": "Week 1", "detail": "Jul 24-Sep 6", "value": "1", "startDate": "2021-07-24T07:00Z", "endDate": "2021-09-07T06:59Z"}, {"label": "Week 2", "alternateLabel": "Week 2", "detail": "Sep 7-13", "value": "2", "startDate": "2021-09-07T07:00Z", "endDate": "2021-09-14T06:59Z"}, {"label": "Week 3", "alternateLabel": "Week 3", "detail": "Sep 14-20", "value": "3", "startDate": "2021-09-14T07:00Z", "endDate": "2021-09-21T06:59Z"}, {"label": "Week 4", "alternateLabel": "Week 4", "detail": "Sep 21-27", "value": "4", "startDate": "2021-09-21T07:00Z", "endDate": "2021-09-28T06:59Z"}, {"label": "Week 5", "alternateLabel": "Week 5", "detail": "Sep 28-Oct 4", "value": "5", "startDate": "2021-09-28T07:00Z", "endDate": "2021-10-05T06:59Z"}, {"label": "Week 6", "alternateLabel": "Week 6", "detail": "Oct 5-11", "value": "6", "startDate": "2021-10-05T07:00Z", "endDate": "2021-10-12T06:59Z"}, {"label": "Week 7", "alternateLabel": "Week 7", "detail": "Oct 12-18", "value": "7", "startDate": "2021-10-12T07:00Z", "endDate": "2021-10-19T06:59Z"}, {"label": "Week 8", "alternateLabel": "Week 8", "detail": "Oct 19-25", "value": "8", "startDate": "2021-10-19T07:00Z", "endDate": "2021-10-26T06:59Z"}, {"label": "Week 9", "alternateLabel": "Week 9", "detail": "Oct 26-Nov 1", "value": "9", "startDate": "2021-10-26T07:00Z", "endDate": "2021-11-02T06:59Z"}, {"label": "Week 10", "alternateLabel": "Week 10", "detail": "Nov 2-8", "value": "10", "startDate": "2021-11-02T07:00Z", "endDate": "2021-11-09T07:59Z"}, {"label": "Week 11", "alternateLabel": "Week 11", "detail": "Nov 9-15", "value": "11", "startDate": "2021-11-09T08:00Z", "endDate": "2021-11-16T07:59Z"}, {"label": "Week 12", "alternateLabel": "Week 12", "detail": "Nov 16-22", "value": "12", "startDate": "2021-11-16T08:00Z", "endDate": "2021-11-23T07:59Z"}, {"label": "Week 13", "alternateLabel": "Week 13", "detail": "Nov 23-29", "value": "13", "startDate": "2021-11-23T08:00Z", "endDate": "2021-11-30T07:59Z"}, {"label": "Week 14", "alternateLabel": "Week 14", "detail": "Nov 30-Dec 6", "value": "14", "startDate": "2021-11-30T08:00Z", "endDate": "2021-12-07T07:59Z"}, {"label": "Week 15", "alternateLabel": "Week 15", "detail": "Dec 7-16", "value": "15", "startDate": "2021-12-07T08:00Z", "endDate": "2021-12-17T07:59Z"}]}, {"label": "Postseason", "value": "3", "startDate": "2021-12-17T08:00Z", "endDate": "2022-01-12T07:59Z", "entries": [{"label": "Bowls", "alternateLabel": "Bowls", "detail": "Dec 17-Jan 11", "value": "1", "startDate": "2021-12-17T08:00Z", "endDate": "2022-01-12T07:59Z"}]}, {"label": "Off Season", "value": "4", "startDate": "2022-01-12T08:00Z", "endDate": "2022-07-01T06:59Z", "entries": [{"label": "All-Star", "alternateLabel": "All-Star", "detail": "Jan 12-Jun 30", "value": "1", "startDate": "2022-01-12T08:00Z", "endDate": "2022-07-01T06:59Z"}]}]}], "events": [{"id": "401309620", "uid": "s:20~l:23~e:401309620", "date": "2021-10-12T23:30Z", "name": "Appalachian State Mountaineers at Louisiana Ragin' Cajuns", "shortName": "APP @ UL", "season": {"year": 2021, "type": 2, "slug": "regular-season"}, "week": {"number": 7}, "competitions": [{"id": "401309620", "uid": "s:20~l:23~e:401309620~c:401309620", "date": "2021-10-12T23:30Z", "attendance": 20066, "type": {"id": "1", "abbreviation": "STD"}, "timeValid": true, "neutralSite": false, "conferenceCompetition": true, "playByPlayAvailable": true, "recent": false, "venue": {"id": "3666", "fullName": "Cajun Field", "address": {"city": "Lafayette", "state": "LA"}, "capacity": 41426, "indoor": false}, "competitors": [{"id": "309", "uid": "s:20~l:23~t:309", "type": "team", "order": 0, "homeAway": "home", "winner": true, "team": {"id": "309", "uid": "s:20~l:23~t:309", "location": "Louisiana", "name": "Ragin' Cajuns", "abbreviation": "UL", "displayName": "Louisiana Ragin' Cajuns", "shortDisplayName": "Ragin' Cajuns", "color": "ce2842", "isActive": true, "venue": {"id": "3666"}, "links": [{"rel": ["clubhouse", "desktop", "team"], "href": "https://www.espn.com/college-football/team/_/id/309/louisiana-ragin-cajuns", "text": "Clubhouse", "isExternal": false, "isPremium": false}, {"rel": ["clubhouse", "mobile", "team"], "href": "http://www.espn.com/college-football/team/_/id/309/louisiana-ragin-cajuns", "text": "Clubhouse", "isExternal": false, "isPremium": false}, {"rel": ["roster", "desktop", "team"], "href": "http://www.espn.com/college-football/team/roster/_/id/309", "text": "Roster", "isExternal": false, "isPremium": false}, {"rel": ["stats", "desktop", "team"], "href": "http://www.espn.com/college-football/team/stats/_/id/309", "text": "Statistics", "isExternal": false, "isPremium": false}, {"rel": ["schedule", "desktop", "team"], "href": "http://www.espn.com/college-football/team/schedule/_/id/309", "text": "Schedule", "isExternal": false, "isPremium": false}, {"rel": ["photos", "desktop", "team"], "href": "http://www.espn.com/college-football/team/photos/_/id/309", "text": "photos", "isExternal": false, "isPremium": false}, {"rel": ["scores", "sportscenter", "app", "team"], "href": "sportscenter://x-callback-url/showClubhouse?uid=s:20~l:23~t:309&section=scores", "text": "Scores", "isExternal": false, "isPremium": false}, {"rel": ["awards", "desktop", "team"], "href": "http://www.espn.com/college-football/awards/_/team/309", "text": "Awards", "isExternal": false, "isPremium": false}], "logo": "https://a.espncdn.com/i/teamlogos/ncaa/500/309.png", "conferenceId": "37"}, "score": "41", "linescores": [{"value": 20.0}, {"value": 0.0}, {"value": 7.0}, {"value": 14.0}], "statistics": [], "curatedRank": {"current": 99}, "records": [{"name": "overall", "abbreviation": "Game", "type": "total", "summary": "5-1"}, {"name": "Home", "type": "home", "summary": "3-0"}, {"name": "Road", "type": "road", "summary": "2-1"}, {"name": "vs. Conf.", "type": "vsconf", "summary": "3-0"}]}, {"id": "2026", "uid": "s:20~l:23~t:2026", "type": "team", "order": 1, "homeAway": "away", "winner": false, "team": {"id": "2026", "uid": "s:20~l:23~t:2026", "location": "Appalachian State", "name": "Mountaineers", "abbreviation": "APP", "displayName": "Appalachian State Mountaineers", "shortDisplayName": "Mountaineers", "color": "000000", "alternateColor": "ffcd00", "isActive": true, "venue": {"id": "3792"}, "links": [{"rel": ["clubhouse", "desktop", "team"], "href": "https://www.espn.com/college-football/team/_/id/2026/appalachian-state-mountaineers", "text": "Clubhouse", "isExternal": false, "isPremium": false}, {"rel": ["clubhouse", "mobile", "team"], "href": "http://www.espn.com/college-football/team/_/id/2026/appalachian-state-mountaineers", "text": "Clubhouse", "isExternal": false, "isPremium": false}, {"rel": ["roster", "desktop", "team"], "href": "http://www.espn.com/college-football/team/roster/_/id/2026", "text": "Roster", "isExternal": false, "isPremium": false}, {"rel": ["stats", "desktop", "team"], "href": "http://www.espn.com/college-football/team/stats/_/id/2026", "text": "Statistics", "isExternal": false, "isPremium": false}, {"rel": ["schedule", "desktop", "team"], "href": "http://www.espn.com/college-football/team/schedule/_/id/2026", "text": "Schedule", "isExternal": false, "isPremium": false}, {"rel": ["photos", "desktop", "team"], "href": "http://www.espn.com/college-football/team/photos/_/id/2026", "text": "photos", "isExternal": false, "isPremium": false}, {"rel": ["scores", "sportscenter", "app", "team"], "href": "sportscenter://x-callback-url/showClubhouse?uid=s:20~l:23~t:2026&section=scores", "text": "Scores", "isExternal": false, "isPremium": false}, {"rel": ["awards", "desktop", "team"], "href": "http://www.espn.com/college-football/awards/_/team/2026", "text": "Awards", "isExternal": false, "isPremium": false}], "logo": "https://a.espncdn.com/i/teamlogos/ncaa/500/2026.png", "conferenceId": "37"}, "score": "13", "linescores": [{"value": 3.0}, {"value": 3.0}, {"value": 7.0}, {"value": 0.0}], "statistics": [], "curatedRank": {"current": 99}, "records": [{"name": "overall", "abbreviation": "Game", "type": "total", "summary": "4-2"}, {"name": "Home", "type": "home", "summary": "2-0"}, {"name": "Road", "type": "road", "summary": "1-2"}, {"name": "vs. Conf.", "type": "vsconf", "summary": "1-1"}]}], "notes": [], "status": {"clock": 0.0, "displayClock": "0:00", "period": 4, "type": {"id": "3", "name": "STATUS_FINAL", "state": "post", "completed": true, "description": "Final", "detail": "Final", "shortDetail": "Final"}}, "broadcasts": [{"market": "national", "names": ["ESPN2"]}], "leaders": [{"name": "passingYards", "displayName": "Passing Leader", "shortDisplayName": "PASS", "abbreviation": "PYDS", "leaders": [{"displayValue": "209 YDS, 1 TD, 1 INT", "value": 209.0, "athlete": {"id": "4241556", "fullName": "Levi Lewis", "displayName": "Levi Lewis", "shortName": "L. Lewis", "links": [{"rel": ["playercard", "desktop", "athlete"], "href": "http://www.espn.com/college-football/player/_/id/4241556/levi-lewis"}, {"rel": ["stats", "desktop", "athlete"], "href": "http://www.espn.com/college-football/player/stats/_/id/4241556/levi-lewis"}, {"rel": ["splits", "desktop", "athlete"], "href": "http://www.espn.com/college-football/player/splits/_/id/4241556/levi-lewis"}, {"rel": ["gamelog", "desktop", "athlete"], "href": "http://www.espn.com/college-football/player/gamelog/_/id/4241556/levi-lewis"}, {"rel": ["news", "desktop", "athlete"], "href": "http://www.espn.com/college-football/player/news/_/id/4241556/levi-lewis"}, {"rel": ["bio", "desktop", "athlete"], "href": "http://www.espn.com/college-football/player/bio/_/id/4241556/levi-lewis"}, {"rel": ["overview", "desktop", "athlete"], "href": "http://www.espn.com/college-football/player/_/id/4241556/levi-lewis"}], "headshot": "https://a.espncdn.com/i/headshots/college-football/players/full/4241556.png", "jersey": "1", "position": {"abbreviation": "QB"}, "team": {"id": "309"}, "active": false}, "team": {"id": "309"}}]}, {"name": "rushingYards", "displayName": "Rushing Leader", "shortDisplayName": "RUSH", "abbreviation": "RYDS", "leaders": [{"displayValue": "14 CAR, 103 YDS, 1 TD", "value": 103.0, "athlete": {"id": "4684625", "fullName": "Montrell Johnson Jr.", "displayName": "Montrell Johnson Jr.", "shortName": "M. Johnson Jr.", "links": [{"rel": ["playercard", "desktop", "athlete"], "href": "http://www.espn.com/college-football/player/_/id/4684625/montrell-johnson-jr"}, {"rel": ["stats", "desktop", "athlete"], "href": "http://www.espn.com/college-football/player/stats/_/id/4684625/montrell-johnson-jr"}, {"rel": ["splits", "desktop", "athlete"], "href": "http://www.espn.com/college-football/player/splits/_/id/4684625/montrell-johnson-jr"}, {"rel": ["gamelog", "desktop", "athlete"], "href": "http://www.espn.com/college-football/player/gamelog/_/id/4684625/montrell-johnson-jr"}, {"rel": ["news", "desktop", "athlete"], "href": "http://www.espn.com/college-football/player/news/_/id/4684625/montrell-johnson-jr"}, {"rel": ["bio", "desktop", "athlete"], "href": "http://www.espn.com/college-football/player/bio/_/id/4684625/montrell-johnson-jr"}, {"rel": ["overview", "desktop", "athlete"], "href": "http://www.espn.com/college-football/player/_/id/4684625/montrell-johnson-jr"}], "headshot": "https://a.espncdn.com/i/headshots/college-football/players/full/4684625.png", "jersey": "2", "position": {"abbreviation": "RB"}, "team": {"id": "309"}, "active": true}, "team": {"id": "309"}}]}, {"name": "receivingYards", "displayName": "Receiving Leader", "shortDisplayName": "REC", "abbreviation": "RECYDS", "leaders": [{"displayValue": "2 REC, 57 YDS, 1 TD", "value": 57.0, "athlete": {"id": "4431219", "fullName": "Kyren Lacy", "displayName": "Kyren Lacy", "shortName": "K. Lacy", "links": [{"rel": ["playercard", "desktop", "athlete"], "href": "http://www.espn.com/college-football/player/_/id/4431219/kyren-lacy"}, {"rel": ["stats", "desktop", "athlete"], "href": "http://www.espn.com/college-football/player/stats/_/id/4431219/kyren-lacy"}, {"rel": ["splits", "desktop", "athlete"], "href": "http://www.espn.com/college-football/player/splits/_/id/4431219/kyren-lacy"}, {"rel": ["gamelog", "desktop", "athlete"], "href": "http://www.espn.com/college-football/player/gamelog/_/id/4431219/kyren-lacy"}, {"rel": ["news", "desktop", "athlete"], "href": "http://www.espn.com/college-football/player/news/_/id/4431219/kyren-lacy"}, {"rel": ["bio", "desktop", "athlete"], "href": "http://www.espn.com/college-football/player/bio/_/id/4431219/kyren-lacy"}, {"rel": ["overview", "desktop", "athlete"], "href": "http://www.espn.com/college-football/player/_/id/4431219/kyren-lacy"}], "headshot": "https://a.espncdn.com/i/headshots/college-football/players/full/4431219.png", "jersey": "2", "position": {"abbreviation": "WR"}, "team": {"id": "309"}, "active": true}, "team": {"id": "309"}}]}], "groups": {"id": "37", "name": "Sun Belt Conference", "shortName": "Sun Belt", "isConference": true}, "format": {"regulation": {"periods": 4}}, "startDate": "2021-10-12T23:30Z", "geoBroadcasts": [{"type": {"id": "1", "shortName": "TV"}, "market": {"id": "1", "type": "National"}, "media": {"shortName": "ESPN2"}, "lang": "en", "region": "us"}], "headlines": [{"description": "\u2014 Levi Lewis threw for one touchdown and ran for another, Chris Smith added two rushing scores and Louisiana-Lafayette eased by Appalachian State 41-13 on Tuesday night.", "type": "Recap", "shortLinkText": "Louisiana-Lafayette uses 4 takeaways to beat App State 41-13", "video": [{"id": 32391438, "source": "espn", "headline": "Appalachian State Mountaineers vs. Louisiana Ragin' Cajuns: Full Highlights", "thumbnail": "https://a.espncdn.com/media/motion/2021/1012/ss_20211012_230059862_1775815/ss_20211012_230059862_1775815.jpg", "duration": 110, "tracking": {"sportName": "ncf", "leagueName": "No League", "coverageType": "Final Game Highlight", "trackingName": "COM_NCF Highlight (Appalachian State Mountaineers vs. Louisiana Ragin' Cajuns: Full Highlights) 2021/10/12 ESHEET Sotfull", "trackingId": "dm_20211012_NCF_appalachian_state_mountaineers_vs_louisiana_ragin_cajuns_full_highlights"}, "deviceRestrictions": {"type": "whitelist", "devices": ["desktop", "settop", "handset", "tablet"]}, "links": {"api": {"self": {"href": "http://api.espn.com/v1/video/clips/32391438"}, "artwork": {"href": "https://artwork.api.espn.com/artwork/collections/media/3d4bd274-b782-4fb8-80b7-d17b00bed131"}}, "web": {"href": "http://www.espn.com/video/clip?id=32391438&ex_cid=espnapi_internal", "short": {"href": "http://www.espn.com/video/clip?id=32391438"}, "self": {"href": "http://www.espn.com/video/clip?id=32391438&ex_cid=espnapi_internal"}}, "source": {"mezzanine": {"href": "https://media.video-origin.espn.com/espnvideo/2021/1012/ss_20211012_230059862_1775815/ss_20211012_230059862_1775815.mp4"}, "flash": {"href": "https://media.video-cdn.espn.com/motion/2021/1012/ss_20211012_230059862_1775815/ss_20211012_230059862_1775815.smil"}, "hds": {"href": "https://hds.video-cdn.espn.com/z/motion/2021/1012/ss_20211012_230059862_1775815/ss_20211012_230059862_1775815_rel.smil/manifest.f4m"}, "HLS": {"href": "https://service-pkgespn.akamaized.net/opp/hls/espn/2021/1012/ss_20211012_230059862_1775815/ss_20211012_230059862_1775815/playlist.m3u8", "HD": {"href": "https://service-pkgespn.akamaized.net/opp/hls/espn/2021/1012/ss_20211012_230059862_1775815/ss_20211012_230059862_1775815/playlist.m3u8"}}, "HD": {"href": "https://media.video-cdn.espn.com/motion/2021/1012/ss_20211012_230059862_1775815/ss_20211012_230059862_1775815_720p30_2896k.mp4"}, "full": {"href": "https://media.video-cdn.espn.com/motion/2021/1012/ss_20211012_230059862_1775815/ss_20211012_230059862_1775815_360p30_1464k.mp4"}, "href": "https://media.video-cdn.espn.com/motion/2021/1012/ss_20211012_230059862_1775815/ss_20211012_230059862_1775815_360p30_1464k.mp4"}, "mobile": {"alert": {"href": "http://m.espn.go.com/general/video/videoAlert?vid=32391438&ex_cid=espnapi_internal"}, "source": {"href": "https://media.video-cdn.espn.com/motion/2021/1012/ss_20211012_230059862_1775815/ss_20211012_230059862_1775815.mp4"}, "href": "https://watch.auth.api.espn.com/video/auth/brightcove/3d4bd274-b782-4fb8-80b7-d17b00bed131/asset?UMADPARAMreferer=http://www.espn.com/video/clip?id=32391438", "streaming": {"href": "https://watch.auth.api.espn.com/video/auth/brightcove/3d4bd274-b782-4fb8-80b7-d17b00bed131/asset?UMADPARAMreferer=http://www.espn.com/video/clip?id=32391438"}, "progressiveDownload": {"href": "https://watch.auth.api.espn.com/video/auth/brightcove/3d4bd274-b782-4fb8-80b7-d17b00bed131/asset?UMADPARAMreferer=http://www.espn.com/video/clip?id=32391438"}}}}]}]}], "links": [{"language": "en-US", "rel": ["summary", "desktop", "event"], "href": "https://www.espn.com/college-football/game/_/gameId/401309620", "text": "Gamecast", "shortText": "Gamecast", "isExternal": false, "isPremium": false}, {"language": "en-US", "rel": ["boxscore", "desktop", "event"], "href": "https://www.espn.com/college-football/boxscore/_/gameId/401309620", "text": "Box Score", "shortText": "Box Score", "isExternal": false, "isPremium": false}, {"language": "en-US", "rel": ["highlights", "desktop"], "href": "https://www.espn.com/college-football/video?gameId=401309620", "text": "Highlights", "shortText": "Highlights", "isExternal": false, "isPremium": false}, {"language": "en-US", "rel": ["pbp", "desktop", "event"], "href": "https://www.espn.com/college-football/playbyplay/_/gameId/401309620", "text": "Play-by-Play", "shortText": "Play-by-Play", "isExternal": false, "isPremium": false}, {"language": "en-US", "rel": ["recap", "desktop", "event"], "href": "https://www.espn.com/college-football/recap?gameId=401309620", "text": "Recap", "shortText": "Recap", "isExternal": false, "isPremium": false}], "status": {"clock": 0.0, "displayClock": "0:00", "period": 4, "type": {"id": "3", "name": "STATUS_FINAL", "state": "post", "completed": true, "description": "Final", "detail": "Final", "shortDetail": "Final"}}}]}